aiotense/__init__.py
aiotense/adapters/__init__.py
aiotense/adapters/converters.py
aiotense/adapters/parsers.py
aiotense/adapters/repository.py
aiotense/application/__init__.py
aiotense/application/exceptions.py
aiotense/application/factory.py
aiotense/application/ports/converters.py
aiotense/application/ports/parsers.py
aiotense/application/ports/repository.py
aiotense/application/resolvers.py
aiotense/domain/model.py
aiotense/domain/units.py
aiotense/service_layer/__init__.py
aiotense/service_layer/dot_tense/__init__.py
aiotense/service_layer/dot_tense/converters.py
aiotense/service_layer/dot_tense/domain.py
aiotense/service_layer/dot_tense/exceptions.py
aiotense/service_layer/dot_tense/step_chain.py
aiotense/service_layer/functional.py
aiotense/service_layer/safe_eval.py
aiotense/service_layer/unit_of_work.py
LICENSE
aiotense-0.0.3a0.dist-info/LICENSE
aiotense-0.0.3a0.dist-info/WHEEL
aiotense-0.0.3a0.dist-info/METADATA
aiotense-0.0.3a0.dist-info/RECORD
