Metadata-Version: 2.1
Name: aiotense
Version: 0.0.3a0
Summary: Time Processing Tool
Home-page: https://github.com/Animatea/aiotense
License: Apache-2.0
Keywords: parser,tool,aiotense,time,utility
Author: Animatea
Author-email: animatea.programming@gmail.com
Requires-Python: >=3.9,<4.0
Classifier: Development Status :: 3 - Alpha
Classifier: License :: OSI Approved :: Apache Software License
Classifier: Natural Language :: English
Classifier: Operating System :: OS Independent
Classifier: Programming Language :: Python :: 3
Classifier: Programming Language :: Python :: 3.10
Classifier: Programming Language :: Python :: 3.9
Classifier: Programming Language :: Python :: Implementation :: CPython
Classifier: Topic :: Software Development :: Libraries
Classifier: Topic :: Software Development :: Libraries :: Python Modules
Classifier: Topic :: Utilities
Classifier: Typing :: Typed
Project-URL: Bug Tracker, https://github.com/Animatea/aiotense/issues
Project-URL: Documentation, https://animatea.github.io/aiotense/
Project-URL: Repository, https://github.com/Animatea/aiotense
